{
  "_class": "group",
  "booleanOperation": 0,
  "clippingMaskMode": 0,
  "do_objectID": "48209614-0142-4E16-85E2-6500863B46C4",
  "exportOptions": {
    "_class": "exportOptions",
    "exportFormats": [
    ],
    "includedLayerIds": [
    ],
    "layerOptions": 0,
    "shouldTrim": false
  },
  "frame": {
    "_class": "rect",
    "constrainProportions": false,
    "height": 576,
    "width": 1414,
    "x": 0,
    "y": 70
  },
  "groupLayout": {
    "_class": "MSImmutableFreeformGroupLayout"
  },
  "hasClickThrough": false,
  "hasClippingMask": false,
  "isFixedToViewport": false,
  "isFlippedHorizontal": false,
  "isFlippedVertical": false,
  "isLocked": false,
  "isVisible": true,
  "layerListExpandedType": 1,
  "layers": [
    {
      "class": "text",
      "id": "A3518125-136A-4FC2-B423-9AFE00D8C733"
    },
    {
      "class": "text",
      "id": "38677682-9DEE-4E63-96C7-0ECA07BD66AA"
    },
    {
      "class": "group",
      "id": "DD4BF476-989E-4DA1-9935-7416534A5BE5"
    },
    {
      "class": "text",
      "id": "07AB4C8A-0100-40D1-B641-F15D686BD668"
    },
    {
      "class": "group",
      "id": "A17C3521-0A02-4485-8498-30ECCA389B0F"
    }
  ],
  "name": "Header",
  "nameIsFixed": true,
  "resizingConstraint": 63,
  "resizingType": 0,
  "rotation": 0,
  "shouldBreakMaskChain": false,
  "style": {
    "_class": "style",
    "endMarkerType": 0,
    "miterLimit": 10,
    "startMarkerType": 0,
    "windingRule": 1
  }
}