{
  "_class": "shapePath",
  "booleanOperation": -1,
  "clippingMaskMode": 0,
  "do_objectID": "3B8096C2-B8C6-43D1-941A-AD73C45E9662",
  "edited": true,
  "exportOptions": {
    "_class": "exportOptions",
    "exportFormats": [
    ],
    "includedLayerIds": [
    ],
    "layerOptions": 0,
    "shouldTrim": false
  },
  "frame": {
    "_class": "rect",
    "constrainProportions": false,
    "height": 2,
    "width": 21,
    "x": 54,
    "y": 16
  },
  "hasClippingMask": false,
  "isClosed": true,
  "isFixedToViewport": false,
  "isFlippedHorizontal": false,
  "isFlippedVertical": false,
  "isLocked": false,
  "isVisible": true,
  "layerListExpandedType": 1,
  "name": "ear",
  "nameIsFixed": false,
  "pointRadiusBehaviour": 0,
  "points": [
    {
      "_class": "curvePoint",
      "cornerRadius": 0,
      "curveFrom": "{0.051470588235294115, 0}",
      "curveMode": 1,
      "curveTo": "{0.051470588235294115, 0}",
      "hasCurveFrom": false,
      "hasCurveTo": false,
      "point": "{0.051470588235294115, 0}"
    },
    {
      "_class": "curvePoint",
      "cornerRadius": 0,
      "curveFrom": "{0.97695588235294106, 0}",
      "curveMode": 4,
      "curveTo": "{0.94852941176470584, 0}",
      "hasCurveFrom": true,
      "hasCurveTo": false,
      "point": "{0.94852941176470584, 0}"
    },
    {
      "_class": "curvePoint",
      "cornerRadius": 0,
      "curveFrom": "{1, 0.77614285714285813}",
      "curveMode": 2,
      "curveTo": "{1, 0.22385714285714187}",
      "hasCurveFrom": true,
      "hasCurveTo": true,
      "point": "{1, 0.5}"
    },
    {
      "_class": "curvePoint",
      "cornerRadius": 0,
      "curveFrom": "{0.94852941176470584, 1}",
      "curveMode": 4,
      "curveTo": "{0.97695588235294106, 1}",
      "hasCurveFrom": false,
      "hasCurveTo": true,
      "point": "{0.94852941176470584, 1}"
    },
    {
      "_class": "curvePoint",
      "cornerRadius": 0,
      "curveFrom": "{0.02304411764705893, 1}",
      "curveMode": 4,
      "curveTo": "{0.051470588235294115, 1}",
      "hasCurveFrom": true,
      "hasCurveTo": false,
      "point": "{0.051470588235294115, 1}"
    },
    {
      "_class": "curvePoint",
      "cornerRadius": 0,
      "curveFrom": "{0, 0.22385714285714187}",
      "curveMode": 2,
      "curveTo": "{0, 0.77614285714285813}",
      "hasCurveFrom": true,
      "hasCurveTo": true,
      "point": "{0, 0.5}"
    },
    {
      "_class": "curvePoint",
      "cornerRadius": 0,
      "curveFrom": "{0.051470588235294115, 0}",
      "curveMode": 4,
      "curveTo": "{0.02304411764705893, 0}",
      "hasCurveFrom": false,
      "hasCurveTo": true,
      "point": "{0.051470588235294115, 0}"
    }
  ],
  "resizingConstraint": 63,
  "resizingType": 0,
  "rotation": 0,
  "shouldBreakMaskChain": false,
  "style": {
    "_class": "style",
    "blur": {
      "_class": "blur",
      "center": "{0.5, 0.5}",
      "isEnabled": false,
      "motionAngle": 0,
      "radius": 1.5,
      "saturation": 1,
      "type": 0
    },
    "endMarkerType": 0,
    "fills": [
      {
        "_class": "fill",
        "color": {
          "_class": "color",
          "alpha": 1,
          "blue": 0.847,
          "green": 0.847,
          "red": 0.847
        },
        "fillType": 1,
        "gradient": {
          "_class": "gradient",
          "elipseLength": 0,
          "from": "{0.5, 1}",
          "gradientType": 0,
          "stops": [
            {
              "_class": "gradientStop",
              "color": {
                "_class": "color",
                "alpha": 0,
                "blue": 0.8901960784313725,
                "green": 0.8862745098039215,
                "red": 0.8784313725490196
              },
              "position": 0
            },
            {
              "_class": "gradientStop",
              "color": {
                "_class": "color",
                "alpha": 1,
                "blue": 0.92,
                "green": 0.9138666666666667,
                "red": 0.9016000000000001
              },
              "position": 1
            }
          ],
          "to": "{0.5, 0}"
        },
        "isEnabled": true,
        "noiseIndex": 0,
        "noiseIntensity": 0,
        "patternFillType": 0,
        "patternTileScale": 1
      }
    ],
    "innerShadows": [
      {
        "_class": "innerShadow",
        "blurRadius": 0,
        "color": {
          "_class": "color",
          "alpha": 0.01,
          "blue": 0,
          "green": 0,
          "red": 0
        },
        "contextSettings": {
          "_class": "graphicsContextSettings",
          "blendMode": 0,
          "opacity": 1
        },
        "isEnabled": true,
        "offsetX": 0,
        "offsetY": 1,
        "spread": 0
      }
    ],
    "miterLimit": 10,
    "startMarkerType": 0,
    "windingRule": 1
  }
}