{
  "_class": "group",
  "booleanOperation": 0,
  "clippingMaskMode": 0,
  "do_objectID": "627E6CB4-553F-4171-8E54-3DD13BAE8AF5",
  "exportOptions": {
    "_class": "exportOptions",
    "exportFormats": [
    ],
    "includedLayerIds": [
    ],
    "layerOptions": 0,
    "shouldTrim": false
  },
  "frame": {
    "_class": "rect",
    "constrainProportions": false,
    "height": 547,
    "width": 1232,
    "x": 0,
    "y": 411
  },
  "groupLayout": {
    "_class": "MSImmutableFreeformGroupLayout"
  },
  "hasClickThrough": true,
  "hasClippingMask": false,
  "isFixedToViewport": false,
  "isFlippedHorizontal": false,
  "isFlippedVertical": false,
  "isLocked": false,
  "isVisible": true,
  "layerListExpandedType": 0,
  "layers": [
    {
      "class": "bitmap",
      "id": "A4199B42-9611-44FF-AFDA-183CEBC39583"
    },
    {
      "class": "bitmap",
      "id": "E96ED8FB-C347-4AEF-8B13-5F70C720ECE5"
    },
    {
      "class": "bitmap",
      "id": "81CF2C3A-05CA-4EB6-9B4B-8AD708761757"
    },
    {
      "class": "bitmap",
      "id": "00C03BF8-3AAC-4B8B-88B9-25D4A12B34E0"
    },
    {
      "class": "bitmap",
      "id": "E75AD041-FB6E-4714-A7B5-4B086A1B826F"
    },
    {
      "class": "text",
      "id": "CD90B1DF-C65B-4905-95AC-6FF6D87CBB59"
    },
    {
      "class": "text",
      "id": "FE4D5344-A5FA-4B0C-A684-FC4071D770F2"
    },
    {
      "class": "text",
      "id": "634BD040-C560-474C-802A-E3F643C044FF"
    }
  ],
  "name": "Logos",
  "nameIsFixed": true,
  "resizingConstraint": 63,
  "resizingType": 0,
  "rotation": 0,
  "shouldBreakMaskChain": false,
  "style": {
    "_class": "style",
    "endMarkerType": 0,
    "miterLimit": 10,
    "startMarkerType": 0,
    "windingRule": 1
  },
  "userInfo": {
    "com.animaapp.stc-sketch-plugin": {
      "kModelPropertiesKey": {
      }
    }
  }
}